{
  "description": "LOSO completo nos sujeitos de desenvolvimento (70%). Teste final intocado.",
  "artifact_prefix": "etapa14_fast_tcn_b4d85add",
  "model_type": "tcn",
  "n_folds": 8,
  "dev_subject_ids": [
    "02",
    "03",
    "08",
    "09",
    "12",
    "13",
    "14",
    "15"
  ],
  "aggregate": {
    "mae_mean": 0.5564236524084315,
    "mae_std": 0.2725156312898951,
    "rmse_mean": 0.6657838249830068,
    "rmse_std": 0.2975769804005317,
    "r2_mean": 0.42987032818721754,
    "r2_std": 0.39210125759753806,
    "bias_mean": 0.05420395761565118,
    "bias_std": 0.528596375203311
  },
  "per_subject": [
    {
      "val_subject_id": "02",
      "n_train_windows": 1173,
      "n_val_windows": 66,
      "best_epoch": 33,
      "best_val_loss": 0.11081970234711964,
      "mae": 0.3271683901675384,
      "rmse": 0.4115593390388007,
      "rms": 0.4115593390388007,
      "r2": 0.6735077808899781,
      "bias": 0.19973393279916227,
      "mape_pct": 125.20033214665985
    },
    {
      "val_subject_id": "03",
      "n_train_windows": 1174,
      "n_val_windows": 65,
      "best_epoch": 65,
      "best_val_loss": 0.10522045691808064,
      "mae": 0.2971756973074009,
      "rmse": 0.3901824450075036,
      "rms": 0.3901824450075036,
      "r2": 0.8661304681339675,
      "bias": -0.11179014633726089,
      "mape_pct": 69.2992157239695
    },
    {
      "val_subject_id": "08",
      "n_train_windows": 1175,
      "n_val_windows": 64,
      "best_epoch": 23,
      "best_val_loss": 0.06933464854955673,
      "mae": 0.28628033215330406,
      "rmse": 0.36370371486800723,
      "rms": 0.36370371486800723,
      "r2": 0.8469415250591557,
      "bias": -0.08060470313939731,
      "mape_pct": 135.8687469594249
    },
    {
      "val_subject_id": "09",
      "n_train_windows": 1174,
      "n_val_windows": 65,
      "best_epoch": 25,
      "best_val_loss": 0.25448207557201385,
      "mae": 0.5535275722383999,
      "rmse": 0.6259433429237156,
      "rms": 0.6259433429237156,
      "r2": 0.4111807666159901,
      "bias": 0.5131357875760668,
      "mape_pct": 246.3714642431422
    },
    {
      "val_subject_id": "12",
      "n_train_windows": 1176,
      "n_val_windows": 63,
      "best_epoch": 2,
      "best_val_loss": 0.1673215925693512,
      "mae": 0.4701778907108794,
      "rmse": 0.575627482316994,
      "rms": 0.575627482316994,
      "r2": 0.24861097080418604,
      "bias": 0.12634741602837854,
      "mape_pct": 481.5411419232502
    },
    {
      "val_subject_id": "13",
      "n_train_windows": 1174,
      "n_val_windows": 65,
      "best_epoch": 2,
      "best_val_loss": 0.22658804804086685,
      "mae": 0.6111792185693645,
      "rmse": 0.7720511536091147,
      "rms": 0.7720511536091147,
      "r2": 0.6139973294682741,
      "bias": -0.35790326197267486,
      "mape_pct": 399.1244219265373
    },
    {
      "val_subject_id": "14",
      "n_train_windows": 1167,
      "n_val_windows": 72,
      "best_epoch": 16,
      "best_val_loss": 0.6526025036970774,
      "mae": 0.9862047694054868,
      "rmse": 1.115528783527259,
      "rms": 1.115528783527259,
      "r2": -0.1333634909634207,
      "bias": 0.9391544559491363,
      "mape_pct": 204.61217584438094
    },
    {
      "val_subject_id": "15",
      "n_train_windows": 1172,
      "n_val_windows": 67,
      "best_epoch": 17,
      "best_val_loss": 0.5691840847333273,
      "mae": 0.9196753487150782,
      "rmse": 1.0716743385726601,
      "rms": 1.0716743385726601,
      "r2": -0.0880427245103903,
      "bias": -0.7944418199782014,
      "mape_pct": 118.08066551871292
    }
  ],
  "training_config": {
    "loss": "huber",
    "learning_rate": 0.0005,
    "weight_decay": 0.0001,
    "huber_delta": 1.0,
    "batch_size": 32,
    "max_epochs": 300,
    "patience": 30,
    "min_delta": 0.0001,
    "dropout": 0.2,
    "num_workers": 6,
    "pin_memory": false,
    "use_amp": false
  },
  "checkpoints": [
    "C:\\Users\\Hoffmann\\Desktop\\Deep-Learning-UTT\\outputs\\pipeline_dl\\checkpoints\\etapa14_fast_tcn_b4d85add_loso_val_02_best.pt",
    "C:\\Users\\Hoffmann\\Desktop\\Deep-Learning-UTT\\outputs\\pipeline_dl\\checkpoints\\etapa14_fast_tcn_b4d85add_loso_val_03_best.pt",
    "C:\\Users\\Hoffmann\\Desktop\\Deep-Learning-UTT\\outputs\\pipeline_dl\\checkpoints\\etapa14_fast_tcn_b4d85add_loso_val_08_best.pt",
    "C:\\Users\\Hoffmann\\Desktop\\Deep-Learning-UTT\\outputs\\pipeline_dl\\checkpoints\\etapa14_fast_tcn_b4d85add_loso_val_09_best.pt",
    "C:\\Users\\Hoffmann\\Desktop\\Deep-Learning-UTT\\outputs\\pipeline_dl\\checkpoints\\etapa14_fast_tcn_b4d85add_loso_val_12_best.pt",
    "C:\\Users\\Hoffmann\\Desktop\\Deep-Learning-UTT\\outputs\\pipeline_dl\\checkpoints\\etapa14_fast_tcn_b4d85add_loso_val_13_best.pt",
    "C:\\Users\\Hoffmann\\Desktop\\Deep-Learning-UTT\\outputs\\pipeline_dl\\checkpoints\\etapa14_fast_tcn_b4d85add_loso_val_14_best.pt",
    "C:\\Users\\Hoffmann\\Desktop\\Deep-Learning-UTT\\outputs\\pipeline_dl\\checkpoints\\etapa14_fast_tcn_b4d85add_loso_val_15_best.pt"
  ]
}